txy/__init__.py
txy/cli.py
txy/command/__init__.py
txy/command/activate.py
txy/command/create.py
txy/command/current.py
txy/command/info.py
txy/command/list.py
txy/command/remove.py
txy/exception/__init__.py
txy/module/__init__.py
txy/module/logger.py
txy/module/venv.py
txy-0.1.9.dist-info/licenses/LICENSE.txt
txy-0.1.9.dist-info/METADATA
txy-0.1.9.dist-info/WHEEL
txy-0.1.9.dist-info/entry_points.txt
txy-0.1.9.dist-info/top_level.txt
txy-0.1.9.dist-info/RECORD
