Metadata-Version: 2.4
Name: txy
Version: 0.1.9
Summary: Python Virtual Environment Manager.
Home-page: https://github.com/Clivern/Txy/
Author: Clivern
Author-email: hello@clivern.com
License: MIT
Project-URL: Documentation, https://github.com/Clivern/Txy/
Project-URL: Source, https://github.com/Clivern/Txy/
Project-URL: Changelog, https://github.com/Clivern/Txy/blob/main/CHANGELOG.rst
Project-URL: Tracker, https://github.com/Clivern/Txy/issues
Project-URL: Download, https://pypi.org/project/Txy/#files
Platform: any
Classifier: Development Status :: 5 - Production/Stable
Classifier: Programming Language :: Python
Classifier: License :: OSI Approved :: MIT License
License-File: LICENSE.txt
Requires-Dist: click<=8.3.0
Requires-Dist: rich<=14.2.0
Requires-Dist: importlib-metadata<=8.7.0; python_version < "3.8"
Dynamic: license-file
